setup.cfg
setup.py
src/colinws/__init__.py
src/colinws/colinwsConfig.py
src/colinws/colinwsDate.py
src/colinws/colinwsEmail.py
src/colinws/colinwsHost.py
src/colinws/colinwsLogs.py
src/colinws/colinwsUtils.py
src/colinws.egg-info/PKG-INFO
src/colinws.egg-info/SOURCES.txt
src/colinws.egg-info/dependency_links.txt
src/colinws.egg-info/top_level.txt