Metadata-Version: 1.0
Name: colinws
Version: 1.0.9
Summary: tools for work
Home-page: http://www.jianshu.com/u/6d793fbacc88
Author: Colin
Author-email: bsply@126.com
License: MIT
Keywords: python,colin,Colin,colinws,Colinws,ColinwsTools
Platform: Linux
Platform: Unix
